auto_test_common_utils/__init__.py
auto_test_common_utils/aes.py
auto_test_common_utils/api_data.py
auto_test_common_utils/api_request_base.py
auto_test_common_utils/common_config.py
auto_test_common_utils/mysql_operation.py
auto_test_common_utils/obs_operation.py
auto_test_common_utils/redis_operation.py
auto_test_common_utils/tools.py
auto_test_common_utils/yaml_config.py
auto_test_common_utils-0.4.dist-info/METADATA
auto_test_common_utils-0.4.dist-info/WHEEL
auto_test_common_utils-0.4.dist-info/top_level.txt
auto_test_common_utils-0.4.dist-info/RECORD
